callflow_tracer/__init__.py
callflow_tracer/async_tracer.py
callflow_tracer/comparison.py
callflow_tracer/exporter.py
callflow_tracer/flamegraph.py
callflow_tracer/flamegraph_enhanced.py
callflow_tracer/jupyter.py
callflow_tracer/memory_leak_detector.py
callflow_tracer/memory_leak_visualizer.py
callflow_tracer/profiling.py
callflow_tracer/tracer.py
callflow_tracer/tracer_old.py
callflow_tracer/integrations/__init__.py
callflow_tracer/integrations/django_integration.py
callflow_tracer/integrations/fastapi_integration.py
callflow_tracer/integrations/flask_integration.py
callflow_tracer/integrations/psycopg2_integration.py
callflow_tracer/integrations/sqlalchemy_integration.py
callflow_tracer-0.2.5.dist-info/licenses/LICENSE
callflow_tracer-0.2.5.dist-info/METADATA
callflow_tracer-0.2.5.dist-info/WHEEL
callflow_tracer-0.2.5.dist-info/top_level.txt
callflow_tracer-0.2.5.dist-info/RECORD
