Metadata-Version: 2.4
Name: callflow-tracer
Version: 0.2.5
Summary: A lightweight Python library for tracing function call relationships and visualizing them as interactive graphs
Home-page: https://github.com/rajveer43/callflow-tracer
Author: Rajveer Rathod
Author-email: Rajveer Rathod <rathodrajveer1311@gmail.com>
Maintainer-email: Rajveer Rathod <rathodrajveer1311@gmail.com>
License: MIT
Project-URL: Homepage, https://github.com/rajveer43/callflow-tracer
Project-URL: Repository, https://github.com/rajveer43/callflow-tracer
Project-URL: Issues, https://github.com/rajveer43/callflow-tracer/issues
Keywords: tracing,profiling,debugging,call-graph,visualization,performance
Classifier: Development Status :: 4 - Beta
Classifier: Intended Audience :: Developers
Classifier: License :: OSI Approved :: MIT License
Classifier: Programming Language :: Python :: 3.8
Classifier: Programming Language :: Python :: 3.9
Classifier: Programming Language :: Python :: 3.10
Classifier: Programming Language :: Python :: 3.11
Classifier: Programming Language :: Python :: 3.12
Requires-Python: >=3.8
License-File: LICENSE
Requires-Dist: networkx>=2.6
Provides-Extra: dev
Requires-Dist: pytest>=6.0; extra == "dev"
Requires-Dist: pytest-cov; extra == "dev"
Requires-Dist: black; extra == "dev"
Requires-Dist: flake8; extra == "dev"
Dynamic: author
Dynamic: home-page
Dynamic: license-file
Dynamic: requires-python
